MANIFEST.in
README.rst
setup.py
collective/__init__.py
collective.js.extjs.egg-info/PKG-INFO
collective.js.extjs.egg-info/SOURCES.txt
collective.js.extjs.egg-info/dependency_links.txt
collective.js.extjs.egg-info/entry_points.txt
collective.js.extjs.egg-info/namespace_packages.txt
collective.js.extjs.egg-info/not-zip-safe
collective.js.extjs.egg-info/requires.txt
collective.js.extjs.egg-info/top_level.txt
collective/js/__init__.py
collective/js/extjs/__init__.py
collective/js/extjs/configure.zcml
collective/js/extjs/adapter/ext/ext-base-debug.js
collective/js/extjs/adapter/ext/ext-base.js
collective/js/extjs/adapter/jquery/ext-jquery-adapter-debug.js
collective/js/extjs/adapter/jquery/ext-jquery-adapter.js
collective/js/extjs/adapter/prototype/ext-prototype-adapter-debug.js
collective/js/extjs/adapter/prototype/ext-prototype-adapter.js
collective/js/extjs/adapter/yui/ext-yui-adapter-debug.js
collective/js/extjs/adapter/yui/ext-yui-adapter.js
collective/js/extjs/profiles/default/cssregistry.xml
collective/js/extjs/profiles/default/jsregistry.xml
collective/js/extjs/profiles/default/metadata.xml
collective/js/extjs/resources/charts.swf
collective/js/extjs/resources/expressinstall.swf
collective/js/extjs/resources/resources.jsb
collective/js/extjs/resources/css/README.txt
collective/js/extjs/resources/css/debug.css
collective/js/extjs/resources/css/ext-all-notheme.css
collective/js/extjs/resources/css/ext-all.css
collective/js/extjs/resources/css/reset-min.css
collective/js/extjs/resources/css/xtheme-access.css
collective/js/extjs/resources/css/xtheme-blue.css
collective/js/extjs/resources/css/xtheme-gray.css
collective/js/extjs/resources/css/yourtheme.css
collective/js/extjs/resources/css/structure/borders.css
collective/js/extjs/resources/css/structure/box.css
collective/js/extjs/resources/css/structure/button.css
collective/js/extjs/resources/css/structure/combo.css
collective/js/extjs/resources/css/structure/core.css
collective/js/extjs/resources/css/structure/date-picker.css
collective/js/extjs/resources/css/structure/dd.css
collective/js/extjs/resources/css/structure/debug.css
collective/js/extjs/resources/css/structure/dialog.css
collective/js/extjs/resources/css/structure/editor.css
collective/js/extjs/resources/css/structure/form.css
collective/js/extjs/resources/css/structure/grid.css
