Metadata-Version: 1.0
Name: collective.js.extjs
Version: 1.2
Summary: Ext JS 3.4 integration for Plone.
Home-page: https://github.com/4teamwork/collective.js.extjs
Author: 4teamwork GmbH
Author-email: mailto:info@4teamwork.ch
License: GPL2
Keywords: extjs plone
Platform: UNKNOWN
Classifier: Programming Language :: Python
Classifier: Framework :: Plone
Classifier: Framework :: Plone :: 4.1
Classifier: Framework :: Plone :: 4.2
